LICENSE
README.md
setup.py
BDMLtools/__init__.py
BDMLtools/base.py
BDMLtools/config.py
BDMLtools/exception.py
BDMLtools/fun.py
BDMLtools.egg-info/PKG-INFO
BDMLtools.egg-info/SOURCES.txt
BDMLtools.egg-info/dependency_links.txt
BDMLtools.egg-info/requires.txt
BDMLtools.egg-info/top_level.txt
BDMLtools/clearner/__init__.py
BDMLtools/clearner/cleaner.py
BDMLtools/encoder/__init__.py
BDMLtools/encoder/woe.py
BDMLtools/plotter/__init__.py
BDMLtools/plotter/base.py
BDMLtools/plotter/eval.py
BDMLtools/report/__init__.py
BDMLtools/report/report.py
BDMLtools/selector/__init__.py
BDMLtools/selector/bin.py
BDMLtools/selector/bin_fun.py
BDMLtools/selector/embeded.py
BDMLtools/selector/fa.py
BDMLtools/selector/lgbm.py
BDMLtools/selector/logtit.py
BDMLtools/selector/simple.py
BDMLtools/tuner/__init__.py
BDMLtools/tuner/base.py
BDMLtools/tuner/bayesian.py
BDMLtools/tuner/fun.py
BDMLtools/tuner/gridcv.py
BDMLtools/tuner/halvingcv.py
test/__init__.py
test/test_base.py
test/test_clearner.py
test/test_eval.py
test/test_report.py
test/test_selector.py
test/test_tunner.py