Metadata-Version: 2.1
Name: BDMLtools
Version: 0.4.3
Summary: Ml learning tools for busniess data mining
Author: 曾珂
Author-email: zengke403@163.com
Classifier: Development Status :: 3 - Alpha
Classifier: Intended Audience :: Developers
Classifier: License :: OSI Approved :: MIT License
Classifier: Programming Language :: Python :: 3.8
Classifier: Programming Language :: Python :: 3.9
Classifier: Programming Language :: Python :: 3.10
Classifier: Programming Language :: Python :: 3.11
Classifier: Programming Language :: Python :: 3.12
License-File: LICENSE
Requires-Dist: fastparquet>=0.7.1
Requires-Dist: pandas>=1.3.5
Requires-Dist: plotnine>=0.12.4
Requires-Dist: scikit-learn>=1.4.0
Requires-Dist: category_encoders>=2.3.0
Requires-Dist: lightgbm>=3.3.0
Requires-Dist: probatus>=2.0.0
Requires-Dist: mlxtend>=0.19.0
Requires-Dist: scikit-optimize>=0.9.0
Requires-Dist: shap<0.43.0,>=0.41.0
Requires-Dist: IPython
Requires-Dist: openpyxl
Provides-Extra: all
Requires-Dist: fastparquet>=0.7.1; extra == "all"
Requires-Dist: pandas>=1.3.5; extra == "all"
Requires-Dist: plotnine>=0.12.4; extra == "all"
Requires-Dist: scikit-learn>=1.4.0; extra == "all"
Requires-Dist: category_encoders>=2.3.0; extra == "all"
Requires-Dist: lightgbm>=3.3.0; extra == "all"
Requires-Dist: probatus>=2.0.0; extra == "all"
Requires-Dist: mlxtend>=0.19.0; extra == "all"
Requires-Dist: scikit-optimize>=0.9.0; extra == "all"
Requires-Dist: shap<0.43.0,>=0.41.0; extra == "all"
Requires-Dist: IPython; extra == "all"
Requires-Dist: openpyxl; extra == "all"
Requires-Dist: pytest>=6.0.0; extra == "all"
Requires-Dist: pytest-cov>=2.10.0; extra == "all"
Requires-Dist: mock; extra == "all"
Requires-Dist: threadpoolctl>=3.0.0; extra == "all"
Requires-Dist: xgboost>=1.5.0; extra == "all"
Requires-Dist: catboost>=1.1; extra == "all"
